css_html_js_minify/__init__.py
css_html_js_minify/css_minifier.py
css_html_js_minify/html_minifier.py
css_html_js_minify/js_minifier.py
css_html_js_minify/minify.py
css_html_js_minify/variables.py
css_html_js_minify/__pycache__/__init__.cpython-36.opt-2.pyc
css_html_js_minify/__pycache__/css_minifier.cpython-36.opt-2.pyc
css_html_js_minify/__pycache__/html_minifier.cpython-36.opt-2.pyc
css_html_js_minify/__pycache__/js_minifier.cpython-36.opt-2.pyc
css_html_js_minify/__pycache__/minify.cpython-36.opt-2.pyc
css_html_js_minify/__pycache__/variables.cpython-36.opt-2.pyc
css_html_js_minify-2.5.5.dist-info/METADATA
css_html_js_minify-2.5.5.dist-info/RECORD
css_html_js_minify-2.5.5.dist-info/WHEEL
css_html_js_minify-2.5.5.dist-info/entry_points.txt
css_html_js_minify-2.5.5.dist-info/top_level.txt
css_html_js_minify-2.5.5.dist-info/zip-safe
