Metadata-Version: 2.1
Name: css-html-js-minify
Version: 2.5.5
Summary: CSS HTML JS Minifier
Home-page: https://github.com/juancarlospaco/css-html-js-minify#css-html-js-minify
Author: Juan Carlos
Author-email: juancarlospaco@gmail.com
Maintainer: Juan Carlos
Maintainer-email: juancarlospaco@gmail.com
License: GPL-3 LGPL-3 MIT
Download-URL: https://github.com/juancarlospaco/css-html-js-minify#css-html-js-minify
Project-URL: Docs, https://github.com/juancarlospaco/css-html-js-minify/README.md
Project-URL: Bugs, https://github.com/juancarlospaco/css-html-js-minify/issues
Project-URL: C.I., https://travis-ci.org/juancarlospaco/css-html-js-minify
Keywords: python3,argentina,CSS,HTML,JS,Compressor,CSS3,HTML5,Web,Javascript,Minifier,Minify,Uglify,Obfuscator
Platform: Linux
Platform: Darwin
Platform: Windows
Classifier: Development Status :: 5 - Production/Stable
Classifier: Environment :: Console
Classifier: Environment :: Other Environment
Classifier: Intended Audience :: Developers
Classifier: Intended Audience :: Other Audience
Classifier: Natural Language :: English
Classifier: License :: OSI Approved :: GNU General Public License (GPL)
Classifier: License :: OSI Approved :: GNU Library or Lesser General Public License (LGPL)
Classifier: License :: OSI Approved :: GNU Lesser General Public License v3 or later (LGPLv3+)
Classifier: License :: OSI Approved :: GNU General Public License v3 or later (GPLv3+)
Classifier: Operating System :: OS Independent
Classifier: Operating System :: POSIX :: Linux
Classifier: Operating System :: Microsoft :: Windows
Classifier: Operating System :: MacOS :: MacOS X
Classifier: Programming Language :: Python
Classifier: Programming Language :: Python :: 3
Classifier: Programming Language :: Python :: 3 :: Only
Classifier: Programming Language :: Python :: 3.6
Classifier: Programming Language :: Python :: Implementation :: CPython
Classifier: Topic :: Software Development
Requires-Python: >=3.6
